bpack/__init__.py
bpack/ba.py
bpack/bs.py
bpack/codecs.py
bpack/descriptors.py
bpack/enums.py
bpack/np.py
bpack/st.py
bpack/typing.py
bpack/utils.py
bpack/tests/__init__.py
bpack/tests/test_backends_codec.py
bpack/tests/test_codecs.py
bpack/tests/test_decoder_ba.py
bpack/tests/test_decoder_np.py
bpack/tests/test_desctiptor_utils.py
bpack/tests/test_field_descriptor.py
bpack/tests/test_future_annotations.py
bpack/tests/test_packbits.py
bpack/tests/test_record_descriptor.py
bpack/tests/test_typing.py
bpack/tests/test_utils.py
bpack/tools/__init__.py
bpack/tools/codegen.py
bpack/tools/tests/__init__.py
bpack/tools/tests/test_codegen.py
bpack/tools/tests/data/__init__.py
bpack/tools/tests/data/flat.py
bpack/tools/tests/data/nested.py
bpack-1.3.0.dist-info/LICENSE
bpack-1.3.0.dist-info/METADATA
bpack-1.3.0.dist-info/WHEEL
bpack-1.3.0.dist-info/top_level.txt
bpack-1.3.0.dist-info/RECORD
