Metadata-Version: 2.1
Name: bpack
Version: 1.3.0
Summary: Binary data structures (un-)packing library
Author-email: Antonio Valentino <antonio.valentino@tiscali.it>
License: Apache-2.0
Project-URL: Homepage, https://github.com/avalentino/bpack
Project-URL: Documentation, https://bpack.readthedocs.io
Project-URL: Repository, https://github.com/avalentino/bpack.git
Project-URL: Changelog, https://github.com/avalentino/bpack/blob/main/docs/release_notes.rst
Project-URL: Issues, https://github.com/avalentino/bpack/issues
Keywords: binary,struct,descriptor,declarative,bit,unpack,pack
Classifier: Development Status :: 4 - Beta
Classifier: Intended Audience :: Science/Research
Classifier: License :: OSI Approved :: Apache Software License
Classifier: Operating System :: OS Independent
Classifier: Programming Language :: Python :: 3
Classifier: Programming Language :: Python :: 3 :: Only
Classifier: Topic :: Scientific/Engineering
Classifier: Topic :: Utilities
Requires-Python: >=3.9
License-File: LICENSE
Provides-Extra: bs
Requires-Dist: bitstruct; extra == "bs"
Provides-Extra: ba
Requires-Dist: bitarray>=1.5.1; extra == "ba"
Provides-Extra: np
Requires-Dist: numpy; extra == "np"
Provides-Extra: codegen
Requires-Dist: black; extra == "codegen"
Provides-Extra: test
Requires-Dist: pytest; extra == "test"
Requires-Dist: bpack[bs]; extra == "test"
Requires-Dist: bpack[ba]; extra == "test"
Requires-Dist: bpack[np]; extra == "test"
Provides-Extra: full
Requires-Dist: bpack[bs]; extra == "full"
Requires-Dist: bpack[ba]; extra == "full"
Requires-Dist: bpack[np]; extra == "full"
Requires-Dist: bpack[codegen]; extra == "full"
Requires-Dist: bpack[test]; extra == "full"
